{
  "html": [
    {
        "type": "audio",
        "class":"audio",
        "id":"audio-description",
        "src": "",
        "content":""
    },
    {
        "type": "audio",
        "class":"audio",
        "id":"audio-correct",
        "src": "",
        "content":""
    },
    {
        "type": "audio",
        "class":"audio",
        "id":"audio-false",
        "src": "",
        "content":""
    },
    {
      "type": "area",
      "id": "image-area",
      "content": [
        {
          "type": "bold",
          "id": "status-text",
          "content": ""
        },
        {
            "type": "area",
            "id": "image-wrapper",
            "content": [
                {
                    "type": "image",
                    "id": "current-image",
                    "src": "https://media3.giphy.com/media/P3bhrBdWCvek8/giphy.gif?cid=3640f6095bc83d5f2f48586e4d1a114e"
                },
                {
                    "type": "area",
                    "class": "overlay",
                    "id": "image-overlay",
                    "content": []
                },
                {
                    "type": "area",
                    "class": "overlay button",
                    "id": "overlayButton",
                    "content":"&#8594;"
                },
                {
                    "type": "area",
                    "class": "img-button button",
                    "id": "replayButton",
                    "content": "&#x1f50a;"
                },
                {
                    "type": "area",
                    "class": "img-button button",
                    "id": "reportButton",
                    "content": "&#9888;"
                }
            ]
        }
      ]
    },
    {
      "type": "area",
      "id": "status-box"
    },
    {
      "type": "area",
      "id": "typing-area"
    }
  ],
  "css": {
    "#image-area": {
    },
    "#image-wrapper": {
        "position": "relative",
        "display": "inline-block"
    },
    "#current-image": {
        "z-index": "1",
        "max-width":"100vw",
        "max-height":"calc(100vh - 150px)"
    },
    "#image-overlay": {
        "background-color": "rgba(0,0,0,1)",
        "height": "100%",
        "width": "100%",
        "z-index": "2",
        "position": "absolute",
        "top": "0px",
        "left": "0px",
        "display": "none"
    },
    ".button": {
        "height": "40px",
        "width": "40px",
        "background-color": "rgba(255,0,0,0)",
        "position": "absolute",
        "bottom": "40px",
        "border": "red 1px solid",
        "border-radius": "50px",
        "text-align": "center",
        "font-size": "2em",
        "display": "table-cell",
        "vertical-align": "middle",
        "display": "none",
        "z-index": 3
    },
    ".button:hover": {
        "background-color": "rgba(255,0,0,1)"
    },
    "#overlayButton": {
        "height": "50px",
        "width": "50px",
        "left": "calc(50% - 25px)",
        "background-color": "white"
    },
    "#replayButton": {
        "left": "17%"
    },
    "#reportButton": {
        "right": "17%"
    },
    "#content":{
        "display":"none"
    },
    "#sidebar":{
        "width":"100%"
    },
    "header":{
        "height": "40px"
    },
    "#room":{
        "display": "none"
    },
    "audio":{
        "height":"0px"
    }
  },
  "scripts": {
    "document-ready": "image-click-functions",
    "submit-message": "send-message",
    "print-history": "plain-history"
  }
}
